pescador/__init__.py
pescador/core.py
pescador/exceptions.py
pescador/maps.py
pescador/mux.py
pescador/util.py
pescador/version.py
pescador/zmq_stream.py
pescador-3.0.0.dist-info/AUTHORS.md
pescador-3.0.0.dist-info/LICENSE.md
pescador-3.0.0.dist-info/METADATA
pescador-3.0.0.dist-info/WHEEL
pescador-3.0.0.dist-info/top_level.txt
pescador-3.0.0.dist-info/RECORD
